{"bills": [{"consignment_number": "10000000", "date": "30/12/2023", "customer_name": null, "customer_address": null, "customer_telephone": null, "items": [], "total_amount": 0, "service_tax": 0.0, "total_amount_with_tax": 0.0}, {"consignment_number": "10000001", "date": "30/12/2023", "customer_name": null, "customer_address": null, "customer_telephone": null, "items": [], "total_amount": 0, "service_tax": 0.0, "total_amount_with_tax": 0.0}, {"consignment_number": "10000001", "date": "30/12/2023", "customer_name": "test", "customer_address": "test", "customer_telephone": "0123", "items": [{"parcel_number": "P10000001", "receiver_name": "test", "receiver_address": "test", "receiver_telephone": "0123", "zone": "Zone C", "weight": 10.0, "price": 22.0}], "total_amount": 22.0, "service_tax": 1.76, "total_amount_with_tax": 23.76}, {"consignment_number": "10000000", "date": "30/12/2023", "customer_name": null, "customer_address": null, "customer_telephone": null, "items": [], "total_amount": 0, "service_tax": 0.0, "total_amount_with_tax": 0.0}, {"consignment_number": "10000000", "date": "30/12/2023", "customer_name": "test", "customer_address": "test", "customer_telephone": "0123", "items": [{"parcel_number": "P10000000", "receiver_name": "test", "receiver_address": "test", "receiver_telephone": "0123", "zone": "Zone A", "weight": 10.0, "price": 18.0}], "total_amount": 18.0, "service_tax": 1.44, "total_amount_with_tax": 19.44}, {"consignment_number": "10000000", "date": "30/12/2023", "customer_name": null, "customer_address": null, "customer_telephone": null, "items": [], "total_amount": 0, "service_tax": 0.0, "total_amount_with_tax": 0.0}, {"consignment_number": "10000001", "date": "30/12/2023", "customer_name": null, "customer_address": null, "customer_telephone": null, "items": [], "total_amount": 0, "service_tax": 0.0, "total_amount_with_tax": 0.0}]}